adwordspy/__init__.py
adwordspy/__main__.py
adwordspy/adwords.py
adwordspy/cli.py
adwordspy-1.1.0.dist-info/DESCRIPTION.rst
adwordspy-1.1.0.dist-info/METADATA
adwordspy-1.1.0.dist-info/RECORD
adwordspy-1.1.0.dist-info/WHEEL
adwordspy-1.1.0.dist-info/entry_points.txt
adwordspy-1.1.0.dist-info/metadata.json
adwordspy-1.1.0.dist-info/top_level.txt
