Metadata-Version: 2.0
Name: adwordspy
Version: 1.1.0
Summary: Adwords API wrapper
Home-page: https://github.com/MihaZelnik/adwordspy
Author: Miha Zelnik
Author-email: miha.zelnik@gmail.com
License: BSD
Keywords: adwords,api,wrapper,google
Platform: UNKNOWN
Classifier: Development Status :: 5 - Production/Stable
Classifier: Intended Audience :: Developers
Classifier: License :: OSI Approved :: BSD License
Classifier: Operating System :: Unix
Classifier: Operating System :: POSIX
Classifier: Operating System :: Microsoft :: Windows
Classifier: Programming Language :: Python
Classifier: Programming Language :: Python :: 2.7
Classifier: Programming Language :: Python :: 3
Classifier: Programming Language :: Python :: 3.3
Classifier: Programming Language :: Python :: 3.4
Classifier: Programming Language :: Python :: 3.5
Classifier: Programming Language :: Python :: Implementation :: CPython
Classifier: Programming Language :: Python :: Implementation :: PyPy
Classifier: Topic :: Utilities
Requires-Dist: googleads (==4.8.0)
